lazy_ecs/__init__.py
lazy_ecs/aws_service.py
lazy_ecs/ui.py
lazy_ecs/core/__init__.py
lazy_ecs/core/app.py
lazy_ecs/core/aws_console.py
lazy_ecs/core/base.py
lazy_ecs/core/context.py
lazy_ecs/core/navigation.py
lazy_ecs/core/types.py
lazy_ecs/core/utils.py
lazy_ecs/features/__init__.py
lazy_ecs/features/cluster/__init__.py
lazy_ecs/features/cluster/cluster.py
lazy_ecs/features/cluster/ui.py
lazy_ecs/features/container/__init__.py
lazy_ecs/features/container/container.py
lazy_ecs/features/container/models.py
lazy_ecs/features/container/ui.py
lazy_ecs/features/service/__init__.py
lazy_ecs/features/service/actions.py
lazy_ecs/features/service/metrics.py
lazy_ecs/features/service/service.py
lazy_ecs/features/service/ui.py
lazy_ecs/features/task/__init__.py
lazy_ecs/features/task/comparison.py
lazy_ecs/features/task/task.py
lazy_ecs/features/task/ui.py
lazy_ecs-0.7.4.dist-info/METADATA
lazy_ecs-0.7.4.dist-info/WHEEL
lazy_ecs-0.7.4.dist-info/entry_points.txt
lazy_ecs-0.7.4.dist-info/licenses/LICENSE
lazy_ecs-0.7.4.dist-info/RECORD
