Metadata-Version: 2.4
Name: lazy-ecs
Version: 0.7.4
Summary: A CLI tool for working with AWS services
Project-URL: Homepage, https://github.com/vertti/lazy-ecs
Project-URL: Repository, https://github.com/vertti/lazy-ecs
Project-URL: Issues, https://github.com/vertti/lazy-ecs/issues
Project-URL: Documentation, https://github.com/vertti/lazy-ecs#readme
Author-email: Janne Sinivirta <janne.sinivirta@gmail.com>
License-File: LICENSE
Keywords: aws,cli,container,devops,docker,ecs,fargate,interactive,terminal,tui
Classifier: Development Status :: 4 - Beta
Classifier: Environment :: Console
Classifier: Intended Audience :: Developers
Classifier: Intended Audience :: System Administrators
Classifier: License :: OSI Approved :: MIT License
Classifier: Operating System :: OS Independent
Classifier: Programming Language :: Python :: 3
Classifier: Programming Language :: Python :: 3.11
Classifier: Programming Language :: Python :: 3.12
Classifier: Programming Language :: Python :: 3.13
Classifier: Programming Language :: Python :: 3.14
Classifier: Topic :: Software Development :: Libraries :: Python Modules
Classifier: Topic :: System :: Systems Administration
Classifier: Topic :: Utilities
Requires-Python: >=3.11
Requires-Dist: boto3==1.40.45
Requires-Dist: questionary==2.1.1
Requires-Dist: rich==14.1.0
